pyorb/__init__.py
python_orbuculum-0.0.1.dist-info/METADATA
python_orbuculum-0.0.1.dist-info/WHEEL
python_orbuculum-0.0.1.dist-info/licenses/LICENSE.txt
python_orbuculum-0.0.1.dist-info/RECORD
