Metadata-Version: 2.1
Name: python-orbuculum
Version: 0.0.1
Summary: Python interface to liborb
Author-Email: Dave Marples <dave@marples.net>, Vegard Storheil Eriksen <zyp@jvnv.net>
License: BSD-3-Clause
Requires-Python: >=3.10
